testing_tool_theg/__init__.py
testing_tool_theg/testing_tool.py
testing_tool_theg-0.0.3.dist-info/LICENSE
testing_tool_theg-0.0.3.dist-info/METADATA
testing_tool_theg-0.0.3.dist-info/WHEEL
testing_tool_theg-0.0.3.dist-info/top_level.txt
testing_tool_theg-0.0.3.dist-info/RECORD
